kingunit_inspector/__init__.py
kingunit_inspector/inspector.py
kingunit_inspector-0.0.7.dist-info/LICENSE
kingunit_inspector-0.0.7.dist-info/METADATA
kingunit_inspector-0.0.7.dist-info/WHEEL
kingunit_inspector-0.0.7.dist-info/top_level.txt
kingunit_inspector-0.0.7.dist-info/RECORD
