Metadata-Version: 2.1
Name: kingunit-inspector
Version: 0.0.7
Summary: KingUnit Inspector
Author-email: 东南dnf <zjy2414@outlook.com>
License: Apache License
Project-URL: Home, https://github.com/zjy2414
Classifier: License :: OSI Approved :: Apache Software License
License-File: LICENSE
Requires-Dist: requests
